<annotation>
	<folder></folder>
	<filename>_Depth_1687243432771-33349609375000_png.rf.047a58c63ddc2ed8eeb3feff7eb71976.jpg</filename>
	<path>_Depth_1687243432771-33349609375000_png.rf.047a58c63ddc2ed8eeb3feff7eb71976.jpg</path>
	<source>
		<database>roboflow.com</database>
	</source>
	<size>
		<width>640</width>
		<height>640</height>
		<depth>3</depth>
	</size>
	<segmented>0</segmented>
	<object>
		<name>45</name>
		<pose>Unspecified</pose>
		<truncated>0</truncated>
		<difficult>0</difficult>
		<occluded>0</occluded>
		<bndbox>
			<xmin>62</xmin>
			<xmax>336</xmax>
			<ymin>188</ymin>
			<ymax>480</ymax>
		</bndbox>
	</object>
</annotation>
