<annotation>
	<folder></folder>
	<filename>_Depth_1687243088498-89428710937500_png.rf.9938881f2e2e4e9d1c569c77c12a53bc.jpg</filename>
	<path>_Depth_1687243088498-89428710937500_png.rf.9938881f2e2e4e9d1c569c77c12a53bc.jpg</path>
	<source>
		<database>roboflow.com</database>
	</source>
	<size>
		<width>640</width>
		<height>640</height>
		<depth>3</depth>
	</size>
	<segmented>0</segmented>
	<object>
		<name>35</name>
		<pose>Unspecified</pose>
		<truncated>0</truncated>
		<difficult>0</difficult>
		<occluded>0</occluded>
		<bndbox>
			<xmin>248</xmin>
			<xmax>490</xmax>
			<ymin>120</ymin>
			<ymax>438</ymax>
		</bndbox>
	</object>
</annotation>
